[{"Title":"Teen Aunt and niece and nephew","PeopleinThePhoto":"Mabel Avila; Manny Avila; Elsie Gonzalez","FamilyandFriends":"Mabel Avila; Manny Avila; Elsie Gonzalez","Unknowns":"","Topics":"Beach; Vacation","WritingMedia":"Pen; Computer printed","StampColor":"","PenColors":"Blue","CompPrintColors":"Grey","Type":"AGFA","Corners":"Zig-Zag ","Orienation":"Portrait","Size":"4.5 x 7","HowMany":"Group","Frame":"White Frame","Shape":"Rectangle","Color":"Black & White","WritingLocation":"Back","Unix":"-91584000","Date":"February 6 1967","Location":"","Neighborhood_Or_SecondCity":"","City":"Liberta","State":"","Country":"Ecuador","Description":"","ImageUrl1":"Assets/Thumbnails/001_Front.png","ImageUrl2":"","ImageUrl3":"","ImageUrl4":""},{"Title":"WENDY & WILLIAM","PeopleinThePhoto":" Elsie Gonzalez; William Garcia; Wendy Varela","FamilyandFriends":" Elsie Gonzalez; William Garcia; Wendy Varela","Unknowns":"","Topics":"Beach; Vacation","WritingMedia":"Pen; Computer printed","StampColor":"","PenColors":"Blue","CompPrintColors":"Grey","Type":"Kodak","Corners":"Pointed","Orienation":"Portrait","Size":"3.5 x 5","HowMany":"Group","Frame":"White Frame","Shape":"Rectangle","Color":"Color","WritingLocation":"Front and back","Unix":"-91584000","Date":"February 6 1967","Location":"","Neighborhood_Or_SecondCity":"","City":"Liberta","State":"","Country":"Ecuador","Description":"","ImageUrl1":"Assets/Thumbnails/002_Front.png","ImageUrl2":"https://drive.google.com/file/d/1PLG_MHs8E8iITlUxrmmz-gwSpHOzouof/view?usp=sharing","ImageUrl3":"","ImageUrl4":""},{"Title":"The Seagulls","PeopleinThePhoto":"Manny Avila; Eddie Cepeda; Reynaldo Garcia; Sildey Gonzalez; Carol Gonzalez; Annmarie Malpasso; Haydee Varela;  Unknown women; Unknown men","FamilyandFriends":"Manny Avila; Eddie Cepeda; Reynaldo Garcia; Sildey Gonzalez; Carol Gonzalez; Annmarie Malpasso; Haydee Varela","Unknowns":"Unknown women; Unknown men","Topics":"Beach; Vacation","WritingMedia":"Stamp; Computer printed","StampColor":"Blue","PenColors":"","CompPrintColors":"Grey","Type":"Kodak","Corners":"Pointed","Orienation":"Panorama","Size":"10.75 x 3.5","HowMany":"Group","Frame":"No Frame","Shape":"Rectangle","Color":"Color","WritingLocation":"Back","Unix":"428544000","Date":"August 1 1983","Location":"","Neighborhood_Or_SecondCity":"","City":"Punta Carnero","State":"","Country":"Ecuador","Description":"","ImageUrl1":"Assets/Thumbnails/003_Front.png","ImageUrl2":"https://drive.google.com/file/d/11uD5SYGEpkeKwNIrhDSqQZswP75kE-L8/view?usp=sharing","ImageUrl3":"https://drive.google.com/file/d/1xfA4qUu8mgT6BmikqyaV4b2h1AYufMO3/view?usp=sharing","ImageUrl4":""},{"Title":"Two Generations Walking","PeopleinThePhoto":"Franklin Gonzalez; Brigitte Ugarte","FamilyandFriends":"Franklin Gonzalez; Brigitte Ugarte","Unknowns":"","Topics":"Un Paseo; Fashion","WritingMedia":"Computer printed","StampColor":"Blue","PenColors":"","CompPrintColors":"Grey","Type":"Konica","Corners":"Pointed","Orienation":"Portrait","Size":"4 x 6","HowMany":"Two  ","Frame":"No Frame","Shape":"Rectangle","Color":"Color","WritingLocation":"Back","Unix":"994377600","Date":"July 6 2001","Location":"","Neighborhood_Or_SecondCity":"Cypress Hills","City":"Brooklyn","State":"New York","Country":"United States","Description":"","ImageUrl1":"Assets/Thumbnails/004_Front.png","ImageUrl2":"","ImageUrl3":"","ImageUrl4":""},{"Title":"Brother and Sister Graduating","PeopleinThePhoto":"Mabel Avila; Manny Avila","FamilyandFriends":"Mabel Avila; Manny Avila","Unknowns":"","Topics":"Graduation; Professional Portrait; School","WritingMedia":"Stamp; Computer printed","StampColor":"","PenColors":"","CompPrintColors":"Grey","Type":"Kodak","Corners":"Pointed","Orienation":"Portrait","Size":"2.25 x 3.5","HowMany":"Two","Frame":"White Frame","Shape":"Rectangle","Color":"Color","WritingLocation":"Back","Unix":"","Date":"June 4 1905","Location":"IS293","Neighborhood_Or_SecondCity":"Carol Gardens","City":"Brooklyn","State":"New York","Country":"United States","Description":"","ImageUrl1":"Assets/Thumbnails/005_Front.png","ImageUrl2":"","ImageUrl3":"","ImageUrl4":""},{"Title":"La Princessa de Navidad","PeopleinThePhoto":"Mabel Avila; Manny Avila; Group of Kids","FamilyandFriends":"Mabel Avila; Manny Avila; ","Unknowns":"Group of Kids","Topics":"Fashion; Holiday; School","WritingMedia":"Computer printed","StampColor":"","PenColors":"","CompPrintColors":"Grey","Type":"Kodak","Corners":"Pointed","Orienation":"Landscape ","Size":"5 x 3.5","HowMany":"Group","Frame":"White Frame","Shape":"Rectangle","Color":"Color","WritingLocation":"Back","Unix":"","Date":"Unknown","Location":"Abdoncalderon","Neighborhood_Or_SecondCity":"","City":"Guayaquil","State":"","Country":"Ecuador","Description":"","ImageUrl1":"Assets/Thumbnails/006_Front.png","ImageUrl2":"","ImageUrl3":"","ImageUrl4":""},{"Title":"Grandpa's Birthday","PeopleinThePhoto":"Alberto Varela; Brigitte Ugarte","FamilyandFriends":"Alberto Varela; Brigitte Ugarte","Unknowns":"","Topics":"Birthday; En La Casa","WritingMedia":"Stamp; Computer printed","StampColor":"Blue","PenColors":"","CompPrintColors":"Grey; Yellow","Type":"Konica","Corners":"Pointed","Orienation":"Portrait","Size":"4 x 5.75","HowMany":"Two ","Frame":"No Frame","Shape":"Rectangle","Color":"Color","WritingLocation":"Front and back","Unix":"936576000","Date":"September 6 1999","Location":"","Neighborhood_Or_SecondCity":"Cypress Hills","City":"Brooklyn","State":"New York","Country":"United States","Description":"","ImageUrl1":"Assets/Thumbnails/007_Front.png","ImageUrl2":"","ImageUrl3":"","ImageUrl4":""},{"Title":"Brother and Sister Celebrating New Year's","PeopleinThePhoto":"William Gonzalez; Haydee Varela; ","FamilyandFriends":"William Gonzalez; Haydee Varela; ","Unknowns":"","Topics":"En La Casa; Holiday","WritingMedia":"Computer printed","StampColor":"Red","PenColors":"","CompPrintColors":"Grey; Yellow","Type":"Kodak","Corners":"Pointed","Orienation":"N/A","Size":"3.5 x 3.5","HowMany":"Two","Frame":"White Frame","Shape":"Square","Color":"Color","WritingLocation":"Back","Unix":"","Date":"Unknown January","Location":"","Neighborhood_Or_SecondCity":"","City":"Queens","State":"New York","Country":"United States","Description":"","ImageUrl1":"Assets/Thumbnails/008_Front.png","ImageUrl2":"https://drive.google.com/file/d/1O06WDSryY_paLjPMbpvsPpm92x2_WUvY/view?usp=sharing","ImageUrl3":"","ImageUrl4":""},{"Title":"Sizzler's","PeopleinThePhoto":"Mabel Avila; Manny Avila; Reynaldo Garcia; Angelita Gonzalez; Elsie Gonzalez; Mariana Gonzalez; William Gonzalez; Annmarie Malpasso; Haydee Varela; Wendy Varela; Vanessa Vera; Unknown man","FamilyandFriends":"Mabel Avila; Manny Avila; Reynaldo Garcia; Angelita Gonzalez; Elsie Gonzalez; Mariana Gonzalez; William Gonzalez; Annmarie Malpasso; Haydee Varela; Wendy Varela; Vanessa Vera; ","Unknowns":"Unknown man","Topics":"Birthday; Food","WritingMedia":"Computer printed","StampColor":"","PenColors":"","CompPrintColors":"Grey","Type":"AGFA","Corners":"Pointed","Orienation":"Landscape","Size":"6 x 4","HowMany":"Group","Frame":"No Frame","Shape":"Rectangle","Color":"Color ","WritingLocation":"Back","Unix":"","Date":"Unknown","Location":"Sizzler","Neighborhood_Or_SecondCity":"Regal Park","City":"Queens","State":"New York","Country":"United States","Description":"","ImageUrl1":"Assets/Thumbnails/009_Front.png","ImageUrl2":"https://drive.google.com/file/d/1D1s3oaziR6Kytb5I6kr0Bh3zPWjiLbzZ/view?usp=sharing","ImageUrl3":"","ImageUrl4":""},{"Title":"Father and Daughter","PeopleinThePhoto":"Alberto Varela; Wendy Varela","FamilyandFriends":"Alberto Varela; Wendy Varela","Unknowns":"","Topics":"Birthday; En La Casa; Fashion","WritingMedia":"Computer printed","StampColor":"","PenColors":"","CompPrintColors":"Grey","Type":"AGFA","Corners":"Pointed","Orienation":"Landscape","Size":"6 x 4","HowMany":"Two","Frame":"No Frame","Shape":"Rectangle","Color":"Color","WritingLocation":"Back","Unix":"103507200","Date":"April 13 1973","Location":"","Neighborhood_Or_SecondCity":"Cypress Hills","City":"Brooklyn","State":"New York","Country":"United States","Description":"","ImageUrl1":"Assets/Thumbnails/010_Front.png","ImageUrl2":"","ImageUrl3":"","ImageUrl4":""},{"Title":"Getaway","PeopleinThePhoto":"Mabel Avila; Haydee Varela; Wendy Varela","FamilyandFriends":"Mabel Avila; Haydee Varela; Wendy Varela","Unknowns":"","Topics":"Vacation","WritingMedia":"Computer printed","StampColor":"","PenColors":"","CompPrintColors":"Grey; Red","Type":"AGFA","Corners":"Pointed","Orienation":"Landscape","Size":"6 x 4","HowMany":"Group","Frame":"No Frame","Shape":"Rectangle","Color":"Color","WritingLocation":"Front and back","Unix":"812419200","Date":"September 30 1995","Location":"Disney World","Neighborhood_Or_SecondCity":"","City":"Orlando","State":"Florida","Country":"United States","Description":"","ImageUrl1":"Assets/Thumbnails/011_Front.jpeg","ImageUrl2":"","ImageUrl3":"","ImageUrl4":""},{"Title":"Mother and Daughters","PeopleinThePhoto":"Wendy Varela; Mabel Avila; Haydee Varela","FamilyandFriends":"Wendy Varela; Mabel Avila; Haydee Varela","Unknowns":"","Topics":"Vacation","WritingMedia":"Computer printed","StampColor":"","PenColors":"","CompPrintColors":"Grey; Red","Type":"AGFA","Corners":"Pointed","Orienation":"Landscape","Size":"6 x 4","HowMany":"Group","Frame":"No Frame","Shape":"Rectangle","Color":"Color","WritingLocation":"Front and back","Unix":"812419200","Date":"September 30 1995","Location":"Disney World","Neighborhood_Or_SecondCity":"","City":"Orlando","State":"Florida","Country":"United States","Description":"","ImageUrl1":"Assets/Thumbnails/012_Front.png","ImageUrl2":"https://drive.google.com/file/d/1X0sUD1mYKFpiCmgfkZzmuZ2Vf447dm7H/view?usp=sharing","ImageUrl3":"","ImageUrl4":""},{"Title":"WENDY","PeopleinThePhoto":"Wendy Varela","FamilyandFriends":"Wendy Varela","Unknowns":"","Topics":"En La Casa; Vacation","WritingMedia":"Pen; Computer printed","StampColor":"","PenColors":"Blue","CompPrintColors":"Grey","Type":"Kodak","Corners":"Rounded","Orienation":"Landscape","Size":"4.25 x 3.5","HowMany":"One","Frame":"No Frame","Shape":"Rectangle","Color":"Color","WritingLocation":"Front and back","Unix":"","Date":"Unknown","Location":"","Neighborhood_Or_SecondCity":"","City":"Guayaquil","State":"","Country":"Ecuador","Description":"","ImageUrl1":"Assets/Thumbnails/013_Front.png","ImageUrl2":"","ImageUrl3":"","ImageUrl4":""},{"Title":"Birthday Party","PeopleinThePhoto":"Mabel Avila; Manny Avila; Evelyn Gonzalez; Sildey Gonzalez","FamilyandFriends":"Mabel Avila; Manny Avila; Evelyn Gonzalez; Sildey Gonzalez;  ","Unknowns":"","Topics":"Birthday","WritingMedia":"Computer printed","StampColor":"","PenColors":"","CompPrintColors":"Grey","Type":"Kodak","Corners":"Rounded","Orienation":"N/A","Size":"3.25 x 3.25","HowMany":"Group","Frame":"No Frame","Shape":"Square","Color":"Color","WritingLocation":"Back","Unix":"","Date":"Unknown","Location":"","Neighborhood_Or_SecondCity":"","City":"Guayaquil","State":"","Country":"Ecuador","Description":"","ImageUrl1":"Assets/Thumbnails/014_Front.png","ImageUrl2":"","ImageUrl3":"","ImageUrl4":""},{"Title":"Grandpa and His New Granddaughter","PeopleinThePhoto":"Mabel Avila; Alberto Varela; Haydee Varela; Brigitte Ugarte ","FamilyandFriends":"Mabel Avila; Alberto Varela; Haydee Varela; Brigitte Ugarte ","Unknowns":"","Topics":"En La Casa; Vacation","WritingMedia":"Pen; Computer printed","StampColor":"","PenColors":"Blue","CompPrintColors":"Grey; Red","Type":"Konica","Corners":"Pointed","Orienation":"Landscape","Size":"5.75 x 3.5","HowMany":"Group","Frame":"No Frame","Shape":"Rectangle","Color":"Color","WritingLocation":"Front and back","Unix":"929145600","Date":"June 12 1999","Location":"","Neighborhood_Or_SecondCity":"","City":"Centerville","State":"Virginia","Country":"United States","Description":"","ImageUrl1":"Assets/Thumbnails/015_Front.png","ImageUrl2":"","ImageUrl3":"","ImageUrl4":""},{"Title":"Class Picture","PeopleinThePhoto":"Mabel Avila; Manny Avila ; Group of Kids","FamilyandFriends":"Mabel Avila; Manny Avila ","Unknowns":"Group of Kids","Topics":"School; Professional Portrait","WritingMedia":"Pencil","StampColor":"","PenColors":"","CompPrintColors":"","Type":"Unknown","Corners":"Rounded","Orienation":"Landscape","Size":"9.25 x 7","HowMany":"Group","Frame":"No Frame","Shape":"Rectangle","Color":"Black & White","WritingLocation":"Back","Unix":"","Date":"Unknown","Location":"Abdoncalderon","Neighborhood_Or_SecondCity":"","City":"Guayaquil","State":"","Country":"Ecuador","Description":"","ImageUrl1":"Assets/Thumbnails/016_Front.png","ImageUrl2":"https://drive.google.com/file/d/1fZg4rsZWOYheoZtyo566TxHTn0tBiRV-/view?usp=sharing","ImageUrl3":"https://drive.google.com/file/d/1LO4_szn5cCvB87VXlmqD56xIHrpGl3ft/view?usp=sharing","ImageUrl4":"https://drive.google.com/file/d/1yNbsD9GoH36QGTEs7bAEa__1oC8-aa5R/view?usp=sharing"},{"Title":"Phone Call","PeopleinThePhoto":"Wendy Varela","FamilyandFriends":"Wendy Varela","Unknowns":"","Topics":"Babies; Professional Portrait","WritingMedia":"Pen","StampColor":"","PenColors":"Blue","CompPrintColors":"","Type":"Unknown","Corners":"Scalloped","Orienation":"Portrait","Size":"4.5 x 7","HowMany":"One","Frame":"No Frame","Shape":"Rectangle","Color":"Color","WritingLocation":"Front and back","Unix":"184377600","Date":"November 5 1975","Location":"","Neighborhood_Or_SecondCity":"","City":"Guayaquil","State":"","Country":"Ecuador","Description":"","ImageUrl1":"Assets/Thumbnails/017_Front.png","ImageUrl2":"https://drive.google.com/file/d/1uDp0_-dpuvp6XG1s3-kmKU8yRJfmb5r0/view?usp=sharing","ImageUrl3":"","ImageUrl4":""},{"Title":"Siblings at the beach.","PeopleinThePhoto":"Mabel Avila; Manny Avila","FamilyandFriends":"Mabel Avila; Manny Avila","Unknowns":"","Topics":"Beach; Vacation","WritingMedia":"Pen; Computer printed","StampColor":"","PenColors":"Blue","CompPrintColors":"Grey","Type":"AGFA","Corners":"Zig-Zag ","Orienation":"Portrait","Size":"3.5 x 5","HowMany":"Two","Frame":"No Frame","Shape":"Rectangle","Color":"Black & White","WritingLocation":"Back","Unix":"-91584000","Date":"February 6 1967","Location":"","Neighborhood_Or_SecondCity":"","City":"Liberta","State":"","Country":"Ecuador","Description":"","ImageUrl1":"Assets/Thumbnails/018_Front.png","ImageUrl2":"https://drive.google.com/file/d/14m_QmnaopvT3dVrei6AO3BieFTrgXhNY/view?usp=sharing","ImageUrl3":"","ImageUrl4":""},{"Title":"Selfie","PeopleinThePhoto":"Elsie Gonzalez","FamilyandFriends":"Elsie Gonzalez","Unknowns":"","Topics":"Beach; Fashion; Vacation","WritingMedia":"Computer printed","StampColor":"","PenColors":"","CompPrintColors":"Grey","Type":"Kodak","Corners":"Pointed","Orienation":"Portrait","Size":"3.5 x 5","HowMany":"One","Frame":"White Frame","Shape":"Rectangle","Color":"Color","WritingLocation":"Back","Unix":"","Date":"Unknown","Location":"","Neighborhood_Or_SecondCity":"","City":"Ecuador","State":"","Country":"","Description":"","ImageUrl1":"Assets/Thumbnails/019_Front.png","ImageUrl2":"https://drive.google.com/file/d/1dumx18e11JjHPmQjQLeNQ4w8BnIK4nv9/view?usp=sharing","ImageUrl3":"","ImageUrl4":""},{"Title":"Camera Shy","PeopleinThePhoto":"Joshua Varela","FamilyandFriends":"Joshua Varela","Unknowns":"","Topics":"Babies; Professional Portrait; Portrait; Fashion","WritingMedia":"Computer printed","StampColor":"","PenColors":"","CompPrintColors":"Black; Grey","Type":"FUJIFILM","Corners":"Pointed","Orienation":"Portrait","Size":"3.5 x 5","HowMany":"One","Frame":"White Strip","Shape":"Rectangle","Color":"Color","WritingLocation":"Front and back","Unix":"1330560000","Date":"March 1 2012","Location":"","Neighborhood_Or_SecondCity":"","City":"","State":"New York","Country":"United States","Description":"","ImageUrl1":"Assets/Thumbnails/020_Front.png","ImageUrl2":"","ImageUrl3":"","ImageUrl4":""},{"Title":"Brothers Laughing","PeopleinThePhoto":"Mabel Avila; Franklin Gonzalez; Wacho Gonzalez;  Unknown People","FamilyandFriends":"Mabel Avila; Franklin Gonzalez; Wacho Gonzalez;  ","Unknowns":"Unknown People","Topics":"En La Casa","WritingMedia":"Stamp; Computer printed","StampColor":"Red","PenColors":"","CompPrintColors":"Grey","Type":"Kodak","Corners":"Pointed","Orienation":"Landscape","Size":"3.5 x 2.5","HowMany":"Group","Frame":"White","Shape":"Rectangle","Color":"Color","WritingLocation":"Back","Unix":"-36806400","Date":"November 1 1968","Location":"","Neighborhood_Or_SecondCity":"","City":"Guayaquil","State":"","Country":"Ecuador","Description":"","ImageUrl1":"Assets/Thumbnails/021_Front.png","ImageUrl2":"","ImageUrl3":"","ImageUrl4":""},{"Title":"Sobrero","PeopleinThePhoto":"Brigitte Ugarte","FamilyandFriends":"Brigitte Ugarte","Unknowns":"","Topics":"En La Casa; Fashion","WritingMedia":"Computer printed","StampColor":"Blue","PenColors":"","CompPrintColors":"Grey; Yellow","Type":"Konica","Corners":"Pointed","Orienation":"Portrait","Size":"4 x 6","HowMany":"One","Frame":"No Frame","Shape":"Rectangle","Color":"Color","WritingLocation":"Front and back","Unix":"986515200","Date":"April 6 2001","Location":"","Neighborhood_Or_SecondCity":"Cypress Hills","City":"Brooklyn","State":"New York","Country":"United States","Description":"","ImageUrl1":"Assets/Thumbnails/022_Front.png","ImageUrl2":"","ImageUrl3":"","ImageUrl4":""},{"Title":"Mother and Son at Wedding","PeopleinThePhoto":"Manny Avila; Haydee Varela","FamilyandFriends":"Manny Avila; Haydee Varela; ","Unknowns":"","Topics":"Fashion; Professional Portrait; Wedding","WritingMedia":"Computer printed","StampColor":"","PenColors":"","CompPrintColors":"Black; Grey","Type":"FUJIFILM","Corners":"Pointed","Orienation":"Landscape","Size":"6 x 4","HowMany":"Two ","Frame":"No Frame","Shape":"Rectangle","Color":"Black & White","WritingLocation":"Back","Unix":"1080777600","Date":"April 1 2004","Location":"","Neighborhood_Or_SecondCity":"","City":"","State":"Virginia","Country":"United States","Description":"","ImageUrl1":"Assets/Thumbnails/023_Front.jpeg","ImageUrl2":"","ImageUrl3":"","ImageUrl4":""},{"Title":"Amelia and Manolo","PeopleinThePhoto":"Amelia Avila; Mabel Avila; Manny Avila; Jennifer Garcia; William Garcia; Elsie Gonzalez; Franklin Gonzalez; Mariana Salazar; Alberto Varela; Haydee Varela; Wendy Varela; Brigitte Ugarte","FamilyandFriends":"Amelia Avila; Mabel Avila; Manny Avila; Jennifer Garcia; William Garcia; Elsie Gonzalez; Franklin Gonzalez; Mariana Salazar; Alberto Varela; Haydee Varela; Wendy Varela; Brigitte Ugarte","Unknowns":"","Topics":"Fashion; Professional Portrait; Wedding","WritingMedia":"Computer printed","StampColor":"","PenColors":"","CompPrintColors":"Black; Grey","Type":"FUJIFILM","Corners":"Pointed","Orienation":"Landscape","Size":"6 x 4","HowMany":"Group","Frame":"No Frame","Shape":"Rectangle","Color":"Color ","WritingLocation":"Back","Unix":"1080777600","Date":"April 1 2004","Location":"","Neighborhood_Or_SecondCity":"","City":"","State":"Virginia","Country":"United States","Description":"","ImageUrl1":"Assets/Thumbnails/024_Front.jpeg","ImageUrl2":"","ImageUrl3":"","ImageUrl4":""},{"Title":"Mother and Daughter on Swings","PeopleinThePhoto":"Mabel Avila; Brigitte Ugarte","FamilyandFriends":"Mabel Avila; Brigitte Ugarte","Unknowns":"","Topics":"Un Paseo; Vacation","WritingMedia":"Stamp; Computer printed","StampColor":"Blue","PenColors":"","CompPrintColors":"Grey; Yellow","Type":"Konica","Corners":"Pointed","Orienation":"Landscape","Size":"6 x 4","HowMany":"Two","Frame":"No Frame","Shape":"Recangle","Color":"Color","WritingLocation":"Front and back","Unix":"928886400","Date":"September 6 1999","Location":"","Neighborhood_Or_SecondCity":"","City":"San Francisco","State":"California","Country":"United States","Description":"","ImageUrl1":"Assets/Thumbnails/025_Front.png","ImageUrl2":"","ImageUrl3":"","ImageUrl4":""},{"Title":"Twinsies","PeopleinThePhoto":"Mabel Avila; Brigitte Ugarte","FamilyandFriends":"Mabel Avila; Brigitte Ugarte","Unknowns":"","Topics":"Un Paseo; Vacation","WritingMedia":"Stamp; Computer printed","StampColor":"Blue","PenColors":"","CompPrintColors":"Grey; Yellow","Type":"Konica","Corners":"Pointed","Orienation":"Landscape","Size":"6 x 4","HowMany":"Two","Frame":"No Frame","Shape":"Rectangle","Color":"Color","WritingLocation":"Front and back","Unix":"928886400","Date":"September 6 1999","Location":"","Neighborhood_Or_SecondCity":"","City":"San Francisco","State":"California","Country":"United States","Description":"","ImageUrl1":"Assets/Thumbnails/026_Front.png","ImageUrl2":"https://drive.google.com/file/d/1r9pGNEF4-B1Hu2V_xMonRZbm0iHnnF6h/view?usp=sharing","ImageUrl3":"","ImageUrl4":""},{"Title":"Great Grandmas birthday dinner","PeopleinThePhoto":"Manny Avila; William Garcia; Elsie Gonzalez; Annmarie Malpasso; Mariana Salazar; Haydee Varela; Wendy Varela;  ","FamilyandFriends":"Manny Avila; William Garcia; Elsie Gonzalez; Annmarie Malpasso; Mariana Salazar; Haydee Varela; Wendy Varela;  ","Unknowns":"","Topics":"Birthday; En La Casa","WritingMedia":"Stamp; Computer printed","StampColor":"Blue","PenColors":"","CompPrintColors":"Grey","Type":"FUJIFILM","Corners":"Pointed","Orienation":"Landscape","Size":"5 x 3.5","HowMany":"Group","Frame":"No Frame","Shape":"Rectangle","Color":"Color","WritingLocation":"Back","Unix":"673056000","Date":"May 1 1991","Location":"","Neighborhood_Or_SecondCity":"Cypress Hills","City":"Brooklyn","State":"New York","Country":"United States","Description":"","ImageUrl1":"Assets/Thumbnails/027_Front.png","ImageUrl2":"https://drive.google.com/file/d/1fZBLhqAPn929KtrA7VGeScSSloRgX3NU/view?usp=sharing","ImageUrl3":"","ImageUrl4":""},{"Title":"Flower Girls","PeopleinThePhoto":"Meghan Montgomery; Mikhaela Montgomery; Brigitte Ugarte","FamilyandFriends":"Meghan Montgomery; Mikhaela Montgomery; Brigitte Ugarte","Unknowns":"","Topics":"Fashion; Professional Portraits; Wedding","WritingMedia":"Computer printed","StampColor":"","PenColors":"","CompPrintColors":"Black; Grey","Type":"FUJIFILM","Corners":"Pointed","Orienation":"Portrait","Size":"4 x 5.75","HowMany":"Group","Frame":"No Frame","Shape":"Rectangle","Color":"Color","WritingLocation":"Back","Unix":"1080777600","Date":"April 1 2004","Location":"","Neighborhood_Or_SecondCity":"","City":"","State":"Virginia","Country":"United States","Description":"","ImageUrl1":"Assets/Thumbnails/028_Front.jpeg","ImageUrl2":"","ImageUrl3":"","ImageUrl4":""},{"Title":"J is For Joshua","PeopleinThePhoto":"Joshua Varela","FamilyandFriends":"Joshua Varela","Unknowns":"","Topics":"Babies; Professional Portrait; Portrait; Fashion","WritingMedia":"Computer printed","StampColor":"","PenColors":"","CompPrintColors":"Grey","Type":"FUJIFILM","Corners":"Pointed","Orienation":"Portrait","Size":"5 x 7","HowMany":"One","Frame":"No Frame","Shape":"Rectangle","Color":"Color","WritingLocation":"Back","Unix":"1330560000","Date":"March 1 2012","Location":"","Neighborhood_Or_SecondCity":"","City":"","State":"","Country":"","Description":"","ImageUrl1":"Assets/Thumbnails/029_Front.jpeg","ImageUrl2":"","ImageUrl3":"","ImageUrl4":""},{"Title":"6-MESES","PeopleinThePhoto":"Brigitte Ugarte","FamilyandFriends":"Brigitte Ugarte","Unknowns":"","Topics":"Vacation","WritingMedia":"Pen; Stamp; Computer printed","StampColor":"Blue","PenColors":"Blue","CompPrintColors":"Grey; Yellow","Type":"Konica","Corners":"Pointed","Orienation":"Landscape","Size":"5.75 x 4","HowMany":"One","Frame":"No Frame","Shape":"Rectangle","Color":"Color","WritingLocation":"Front and back","Unix":"937785600","Date":"September 20 1999","Location":"Inside a plane from NYC to SF","Neighborhood_Or_SecondCity":"","City":"","State":"","Country":"","Description":"","ImageUrl1":"Assets/Thumbnails/030_Front.jpeg","ImageUrl2":"","ImageUrl3":"","ImageUrl4":""},{"Title":"Buffet","PeopleinThePhoto":"Alberto Varela","FamilyandFriends":"Alberto Varela","Unknowns":"","Topics":"Vacation","WritingMedia":"Computer printed","StampColor":"","PenColors":"","CompPrintColors":"Grey","Type":"Kodak","Corners":"Pointed","Orienation":"Landscape","Size":"4.75 x 3.5","HowMany":"One","Frame":"No Frame","Shape":"Rectangle","Color":"Color","WritingLocation":"Back","Unix":"","Date":"Unknown","Location":"","Neighborhood_Or_SecondCity":"","City":"Orlando","State":"Florida","Country":"","Description":"","ImageUrl1":"Assets/Thumbnails/031_Front.jpeg","ImageUrl2":"","ImageUrl3":"","ImageUrl4":""},{"Title":"First Halloween","PeopleinThePhoto":"Brigitte Ugarte","FamilyandFriends":"Brigitte Ugarte","Unknowns":"","Topics":"Holiday","WritingMedia":"Stamp; Computer printed","StampColor":"Blue","PenColors":"","CompPrintColors":"Grey; Yellow","Type":"Konica","Corners":"Pointed","Orienation":"Landscape","Size":"5.75 x 4","HowMany":"One","Frame":"No Frame","Shape":"Rectangle","Color":"Color","WritingLocation":"Front and back","Unix":"941241600","Date":"October 30 1999","Location":"","Neighborhood_Or_SecondCity":"Cypress Hills","City":"Brooklyn","State":"","Country":"United States","Description":"","ImageUrl1":"Assets/Thumbnails/032_Front.jpeg","ImageUrl2":"","ImageUrl3":"","ImageUrl4":""},{"Title":"Partying Into The New Year","PeopleinThePhoto":"Diana Gonzalez","FamilyandFriends":"Diana Gonzalez","Unknowns":"","Topics":"Holiday; Party","WritingMedia":"Pen; Computer printed","StampColor":"","PenColors":"Black","CompPrintColors":"Gold","Type":"Kodak","Corners":"Pointed","Orienation":"Landscape","Size":"6 x 4","HowMany":"Group","Frame":"No Frame","Shape":"Rectangle","Color":"Color","WritingLocation":"Back","Unix":"","Date":"June 17 1905","Location":"","Neighborhood_Or_SecondCity":"","City":"Guayaquil","State":"","Country":"Ecuador","Description":"","ImageUrl1":"Assets/Thumbnails/033_Front.jpeg","ImageUrl2":"","ImageUrl3":"","ImageUrl4":""},{"Title":"Walking to work","PeopleinThePhoto":"Alberto Varela","FamilyandFriends":"Alberto Varela","Unknowns":"","Topics":"Fashion; Un Paseo; Work","WritingMedia":"Pen; Computer printed","StampColor":"","PenColors":"Blue","CompPrintColors":"Grey","Type":"AGFA","Corners":"Scalloped","Orienation":"Portrait","Size":"2.25 x 3","HowMany":"One","Frame":"White Frame","Shape":"Rectangle","Color":"Black & White","WritingLocation":"Back","Unix":"","Date":"Unknown","Location":"","Neighborhood_Or_SecondCity":"","City":"Cali","State":"","Country":"Colombia","Description":"","ImageUrl1":"Assets/Thumbnails/034_Front.png","ImageUrl2":"","ImageUrl3":"","ImageUrl4":""},{"Title":"Merry Christmas","PeopleinThePhoto":"Wendy Varela","FamilyandFriends":"Wendy Varela","Unknowns":"","Topics":"En La Casa; Holiday","WritingMedia":"Computer printed","StampColor":"","PenColors":"","CompPrintColors":"Grey","Type":"Kodak","Corners":"Pointed","Orienation":"Landscape","Size":"4.75 x 4","HowMany":"One","Frame":"No Frame","Shape":"Rectangle","Color":"Color","WritingLocation":"Back","Unix":"","Date":"Unknown","Location":"","Neighborhood_Or_SecondCity":"Cypress Hills","City":"Brooklyn","State":"","Country":"United States","Description":"","ImageUrl1":"Assets/Thumbnails/035_Front.jpeg","ImageUrl2":"","ImageUrl3":"","ImageUrl4":""},{"Title":"Great Adventure","PeopleinThePhoto":"Alissa; Mabel Avila; Kaye Kongaika; Wendy Varela;  ","FamilyandFriends":"Alissa; Mabel Avila; Kaye Kongaika; Wendy Varela;  ","Unknowns":"","Topics":"Friends; Fun; Vacation","WritingMedia":"Computer printed","StampColor":"","PenColors":"","CompPrintColors":"Grey","Type":"AGFA","Corners":"Pointed","Orienation":"landsacape","Size":"5.75 x 4","HowMany":"Group","Frame":"No Frame","Shape":"Rectangle","Color":"Color","WritingLocation":"Back","Unix":"","Date":"Summer 1991","Location":"Great Adventure","Neighborhood_Or_SecondCity":"","City":"Jackson Township","State":"New Jersey","Country":"United States","Description":"","ImageUrl1":"Assets/Thumbnails/036_Front.jpeg","ImageUrl2":"","ImageUrl3":"","ImageUrl4":""},{"Title":"Daily Routine","PeopleinThePhoto":"Brigitte Ugarte","FamilyandFriends":"Brigitte Ugarte","Unknowns":"","Topics":"En La Casa; Fashion","WritingMedia":"Computer printed","StampColor":"","PenColors":"","CompPrintColors":"Dark Grey; Grey","Type":"Konica","Corners":"Pointed","Orienation":"Portrait","Size":"4 x 5.75","HowMany":"One","Frame":"No Frame","Shape":"Rectangle","Color":"Color","WritingLocation":"Back","Unix":"1009843200","Date":"January 1 2002","Location":"","Neighborhood_Or_SecondCity":"Cypress Hills","City":"Brooklyn","State":"New York","Country":"United States","Description":"","ImageUrl1":"Assets/Thumbnails/037_Front.jpeg","ImageUrl2":"","ImageUrl3":"","ImageUrl4":""},{"Title":"Birthday Party","PeopleinThePhoto":"Brigitte Ugarte; Mabel Avila","FamilyandFriends":"Brigitte Ugarte; Mabel Avila","Unknowns":"","Topics":"Fashion; Birthday","WritingMedia":"Stamp; Computer printed","StampColor":"Blue","PenColors":"","CompPrintColors":"Grey","Type":"Konica","Corners":"Pointed","Orienation":"Landscape","Size":"6 x 4","HowMany":"Two","Frame":"No Frame","Shape":"Rectangle","Color":"Color","WritingLocation":"Front and back","Unix":"986515200","Date":"April 6 2001","Location":"","Neighborhood_Or_SecondCity":"Cypress Hills","City":"Brooklyn","State":"New York","Country":"United States","Description":"","ImageUrl1":"Assets/Thumbnails/038_Front.jpeg","ImageUrl2":"","ImageUrl3":"","ImageUrl4":""},{"Title":"Burger King","PeopleinThePhoto":"Brigitte Ugarte; Mabel Avila","FamilyandFriends":"Brigitte Ugarte; Mabel Avila","Unknowns":"","Topics":"Food; Vacation","WritingMedia":"Stamp; Computer printed","StampColor":"Blue","PenColors":"","CompPrintColors":"Grey; Yellow","Type":"Konica","Corners":"Pointed","Orienation":"Landscape","Size":"5.75 x 4","HowMany":"Two","Frame":"No Frame","Shape":"Rectangle","Color":"Color","WritingLocation":"Front and back","Unix":"936576000","Date":"September 6 1999","Location":"Burger King","Neighborhood_Or_SecondCity":"","City":"San Francisco","State":"California","Country":"United States","Description":"","ImageUrl1":"Assets/Thumbnails/039_Front.jpeg","ImageUrl2":"","ImageUrl3":"","ImageUrl4":""},{"Title":"Prepping for a Snow Day","PeopleinThePhoto":"Elsie Gonzalez; Wendy Varela; Brigitte Ugarte","FamilyandFriends":"Elsie Gonzalez; Wendy Varela; Brigitte Ugarte","Unknowns":"","Topics":"Snow Day; Vacation","WritingMedia":"Stamp; Computer printed","StampColor":"Blue","PenColors":"","CompPrintColors":"Brown; Yellow","Type":"Kodak","Corners":"Pointed","Orienation":"Landscape","Size":"6 x 4","HowMany":"Group","Frame":"No Frame","Shape":"Rectangle","Color":"Color","WritingLocation":"Front and back","Unix":"","Date":"February 1 2001","Location":"","Neighborhood_Or_SecondCity":"","City":"Unknown","State":"","Country":"","Description":"","ImageUrl1":"Assets/Thumbnails/040_Front.jpeg","ImageUrl2":"","ImageUrl3":"","ImageUrl4":""},{"Title":"Little sister","PeopleinThePhoto":"Mabel Avila; Manny Avila;","FamilyandFriends":"Mabel Avila; Manny Avila;","Unknowns":"","Topics":"Babies; Un Paseo","WritingMedia":"Pencil; Computer printed","StampColor":"","PenColors":"","CompPrintColors":"Grey","Type":"AGFA","Corners":"Scalloped","Orienation":"Landscape","Size":"5.25 x 3.25","HowMany":"Two  ","Frame":"White Frame","Shape":"Rectangle","Color":"Black & White","WritingLocation":"Back","Unix":"","Date":"May 17 1905","Location":"","Neighborhood_Or_SecondCity":"","City":"Guayaquil","State":"","Country":"Ecuador","Description":"","ImageUrl1":"Assets/Thumbnails/041_Front.png","ImageUrl2":"","ImageUrl3":"","ImageUrl4":""},{"Title":"WENDY","PeopleinThePhoto":"Mariana Gonzalez; Wendy Varela; Unknown child","FamilyandFriends":"Mariana Gonzalez; Wendy Varela;  ","Unknowns":"Unknown child","Topics":"Babies","WritingMedia":"Pen; Computer printed","StampColor":"","PenColors":"Blue","CompPrintColors":"Grey","Type":"Kodak","Corners":"Zig-Zag ","Orienation":"N/A","Size":"2.5 x 2.5","HowMany":"Group","Frame":"White Frame","Shape":"Square","Color":"Color","WritingLocation":"Back","Unix":"","Date":"May 26 1905","Location":"","Neighborhood_Or_SecondCity":"","City":"Brooklyn","State":"New York","Country":"United States","Description":"","ImageUrl1":"","ImageUrl2":"","ImageUrl3":"","ImageUrl4":""},{"Title":"CHEM SQUAD","PeopleinThePhoto":"Valentina Rojas; Jean Suh; Brigitte Ugarte; Josh Weinfeld","FamilyandFriends":"Valentina Rojas; Jean Suh; Brigitte Ugarte; Josh Weinfeld","Unknowns":"","Topics":"Friends; Fun","WritingMedia":"Sharpie; Computer printed","StampColor":"","PenColors":"Black","CompPrintColors":"White","Type":"FUJIFILM","Corners":"Pointed","Orienation":"Portrait","Size":"2.25 x 3.5","HowMany":"Group","Frame":"White Frame","Shape":"Rectangle","Color":"Color","WritingLocation":"Front and back","Unix":"","Date":"July 7 1905","Location":"","Neighborhood_Or_SecondCity":"","City":"Queens","State":"New York","Country":"United States","Description":"","ImageUrl1":"Assets/Thumbnails/043_Front.jpeg","ImageUrl2":"","ImageUrl3":"","ImageUrl4":""},{"Title":"Jean's 18th birthday","PeopleinThePhoto":"Jean Suh; Brigitte Ugarte  ","FamilyandFriends":"Jean Suh; Brigitte Ugarte;  ","Unknowns":"","Topics":"Fashion; Friends; Birthday","WritingMedia":"Computer printed","StampColor":"","PenColors":"","CompPrintColors":"Black; Blue; Red; Yellow; White","Type":"FUJIFILM","Corners":"Pointed","Orienation":"Portrait","Size":"2.25 x 3.5","HowMany":"Two ","Frame":"Comic Frame","Shape":"Rectangle","Color":"Color","WritingLocation":"Front and back","Unix":"","Date":"July 7 1905","Location":"","Neighborhood_Or_SecondCity":"","City":"New York","State":"New York","Country":"United States","Description":"","ImageUrl1":"Assets/Thumbnails/044_Front.jpeg","ImageUrl2":"","ImageUrl3":"","ImageUrl4":""},{"Title":"Chicas","PeopleinThePhoto":"Alex Altamirano; Brigitte Ugarte","FamilyandFriends":"Alex Altamirano; Brigitte Ugarte","Unknowns":"","Topics":"Fashion; Friends; Birthday","WritingMedia":"Computer printed","StampColor":"","PenColors":"","CompPrintColors":"Black; Blue; Red; Yellow; White","Type":"FUJIFILM","Corners":"Pointed","Orienation":"Portrait","Size":"2.25 x 3.5","HowMany":"Two","Frame":"Comic Frame","Shape":"Rectangle","Color":"Color","WritingLocation":"Front and back","Unix":"","Date":"July 7 1905","Location":"","Neighborhood_Or_SecondCity":"","City":"New York","State":"New York","Country":"United States","Description":"","ImageUrl1":"Assets/Thumbnails/045_Front.jpeg","ImageUrl2":"","ImageUrl3":"","ImageUrl4":""},{"Title":"Blizzard","PeopleinThePhoto":"Haruka Amemiya; Yan Marrero; Brigitte Ugarte","FamilyandFriends":"Haruka Amemiya; Yan Marrero; Brigitte Ugarte","Unknowns":"","Topics":"Friends; Snow Day","WritingMedia":"Computer printed","StampColor":"","PenColors":"","CompPrintColors":"White","Type":"FUJIFILM","Corners":"Pointed","Orienation":"Portrait","Size":"2.25 x 3.5","HowMany":"Group","Frame":"White Frame","Shape":"Rectangle","Color":"Color","WritingLocation":"Back","Unix":"","Date":"July 7 1905","Location":"","Neighborhood_Or_SecondCity":"","City":"New York","State":"New York","Country":"United States","Description":"","ImageUrl1":"Assets/Thumbnails/046_Front.jpeg","ImageUrl2":"","ImageUrl3":"","ImageUrl4":""},{"Title":"Spidey","PeopleinThePhoto":"Joshua Varela","FamilyandFriends":"Joshua Varela","Unknowns":"","Topics":"Fashion; Snow Day","WritingMedia":"Computer printed","StampColor":"","PenColors":"","CompPrintColors":"White","Type":"FUJIFILM","Corners":"Pointed","Orienation":"Portrait","Size":"2.25 x 3.5","HowMany":"One","Frame":"White Frame","Shape":"Rectangle","Color":"Color","WritingLocation":"Back","Unix":"","Date":"July 7 1905","Location":"","Neighborhood_Or_SecondCity":"","City":"Brooklyn","State":"New York","Country":"United States","Description":"","ImageUrl1":"Assets/Thumbnails/047_Front.jpeg","ImageUrl2":"","ImageUrl3":"","ImageUrl4":""},{"Title":"Waterfall shower","PeopleinThePhoto":"Alberto Varela","FamilyandFriends":"Alberto Varela","Unknowns":"","Topics":"Vacation","WritingMedia":"Pen; Computer printed","StampColor":"","PenColors":"Black","CompPrintColors":"Black; Grey","Type":"Kodak","Corners":"Pointed","Orienation":"Landscape","Size":"5.75 x 4","HowMany":"One","Frame":"No Frame","Shape":"Rectangle","Color":"Color","WritingLocation":"Back","Unix":"1188604800","Date":"September 1 2007","Location":"","Neighborhood_Or_SecondCity":"Santa Rosa","City":"Pereira","State":"","Country":"Colombia","Description":"","ImageUrl1":"Assets/Thumbnails/048_Front.png","ImageUrl2":"https://drive.google.com/file/d/1gVNzC6XPwHCDzbvYKt7-ZPrUoEDS7Iaj/view?usp=sharing","ImageUrl3":"","ImageUrl4":""},{"Title":"Family Portrait","PeopleinThePhoto":"Mabel Avila; Manny Avila; Haydee Varela","FamilyandFriends":"Mabel Avila; Manny Avila; Haydee Varela","Unknowns":"","Topics":"Professional Portrait","WritingMedia":"","StampColor":"","PenColors":"","CompPrintColors":"","Type":"Unknown","Corners":"Pointed","Orienation":"Portrait","Size":"3.25 x 4.5","HowMany":"Group","Frame":"White Frame","Shape":"Rectangle","Color":"Black & White","WritingLocation":"","Unix":"","Date":"May 21 1905","Location":"","Neighborhood_Or_SecondCity":"","City":"Guayaquil","State":"","Country":"Ecuador","Description":"","ImageUrl1":"Assets/Thumbnails/049_Front.jpeg","ImageUrl2":"","ImageUrl3":"","ImageUrl4":""},{"Title":"Birthday Cake blowing out candles","PeopleinThePhoto":"Matthew Garcia; Noah Garcia; Ryan Garcia; Joshua Varela","FamilyandFriends":"Matthew Garcia; Noah Garcia; Ryan Garcia; Joshua Varela","Unknowns":"","Topics":"BIrthday","WritingMedia":"Computer printed","StampColor":"","PenColors":"","CompPrintColors":"Grey","Type":"FUJIFILM","Corners":"Pointed","Orienation":"Landscape","Size":"6 x 4","HowMany":"Group","Frame":"White Frame","Shape":"Rectangle","Color":"Color","WritingLocation":"Back","Unix":"","Date":"April 1 2013","Location":"","Neighborhood_Or_SecondCity":"","City":"Brooklyn","State":"New York","Country":"United States","Description":"","ImageUrl1":"Assets/Thumbnails/050_Front.jpeg","ImageUrl2":"","ImageUrl3":"","ImageUrl4":""},{"Title":"Christmas Eve Celebration","PeopleinThePhoto":"Elsie Gonzalez; Alberto Varela; Haydee Varela; Wendy Varela","FamilyandFriends":"Elsie Gonzalez; Alberto Varela; Haydee Varela; Wendy Varela","Unknowns":"","Topics":"Holiday","WritingMedia":"Computer printed","StampColor":"","PenColors":"","CompPrintColors":"Grey; Red","Type":"Kodak","Corners":"Pointed","Orienation":"Landscape","Size":"3.5 x 5","HowMany":"Group","Frame":"No Frame","Shape":"Rectangle","Color":"Color","WritingLocation":"Back","Unix":"819676800","Date":"December 23 1995","Location":"","Neighborhood_Or_SecondCity":"","City":"Farmingdale","State":"New York","Country":"United States","Description":"","ImageUrl1":"Assets/Thumbnails/051_Front.png","ImageUrl2":"https://drive.google.com/file/d/1nNef7IAQu0Zf8QxmqiDbgAk3JWGlBG_U/view?usp=sharing","ImageUrl3":"","ImageUrl4":""},{"Title":"Wendy's brithday","PeopleinThePhoto":"Wendy Varela; Brigitte Ugarte","FamilyandFriends":"Wendy Varela; Brigitte Ugarte","Unknowns":"","Topics":"Babies; Birthday","WritingMedia":"Pen; Computer printed","StampColor":"","PenColors":"Blue","CompPrintColors":"Grey","Type":"Konica","Corners":"Pointed","Orienation":"Landscape","Size":"4.5 x 3.5","HowMany":"Two","Frame":"No Frame","Shape":"Rectangle","Color":"Color","WritingLocation":"Back","Unix":"924307200","Date":"April 17 1999","Location":"","Neighborhood_Or_SecondCity":"","City":"Brooklyn","State":"New York","Country":"United States","Description":"","ImageUrl1":"Assets/Thumbnails/052_Front.png","ImageUrl2":"https://drive.google.com/file/d/1CUAnkKriOlM-T6M8t-2NjHwK1O4BaUSd/view?usp=sharing","ImageUrl3":"","ImageUrl4":""},{"Title":"Nevada del 78 NY","PeopleinThePhoto":"Mabel Avila; Wendy Varela","FamilyandFriends":"Mabel Avila; Wendy Varela","Unknowns":"","Topics":"Fashion; Snow Day","WritingMedia":"Pen; Computer printed","StampColor":"","PenColors":"Blue","CompPrintColors":"Grey","Type":"Kodak","Corners":"Rounded","Orienation":"Landscape","Size":"4.5 x 3.5","HowMany":"Two","Frame":"No Frame","Shape":"Rectangle","Color":"Color","WritingLocation":"Front and back","Unix":"","Date":"May 31 1905","Location":"","Neighborhood_Or_SecondCity":"","City":"Brooklyn","State":"New York","Country":"United States","Description":"","ImageUrl1":"Assets/Thumbnails/053_Front.png","ImageUrl2":"","ImageUrl3":"","ImageUrl4":""},{"Title":"Here comes the Sun","PeopleinThePhoto":"Mabel Avila","FamilyandFriends":"Mabel Avila","Unknowns":"","Topics":"Fashion; School","WritingMedia":"Computer printed","StampColor":"","PenColors":"","CompPrintColors":"Grey","Type":"Kodak","Corners":"Rounded","Orienation":"Landscape","Size":"4 x 6","HowMany":"One","Frame":"No Frame","Shape":"Rectangle","Color":"Color","WritingLocation":"Back","Unix":"486518400","Date":"June 2 1985","Location":"Franklin institute Museum","Neighborhood_Or_SecondCity":"","City":"Philadelphia","State":"Pennsylvania ","Country":"United States","Description":"","ImageUrl1":"Assets/Thumbnails/054_Front.png","ImageUrl2":"","ImageUrl3":"","ImageUrl4":""},{"Title":"Twinning","PeopleinThePhoto":"Alberto Varela; Haydee Varela","FamilyandFriends":"Alberto Varela; Haydee Varela","Unknowns":"","Topics":"Fashion; Vacation","WritingMedia":"Pen; Computer printed","StampColor":"","PenColors":"Black","CompPrintColors":"Black; Grey","Type":"Kodak","Corners":"Pointed","Orienation":"Portrait","Size":"3.5 x 3.5","HowMany":"Two","Frame":"No Frame","Shape":"Rectangle","Color":"Color","WritingLocation":"Back","Unix":"1188604800","Date":"September 1 2007","Location":"","Neighborhood_Or_SecondCity":"","City":"Buga","State":"","Country":"Colombia","Description":"","ImageUrl1":"Assets/Thumbnails/055_Front.png","ImageUrl2":"","ImageUrl3":"","ImageUrl4":""},{"Title":"Siblings celebrating Holiday","PeopleinThePhoto":"Haydee Varela; Wacho Gonzalez","FamilyandFriends":"Haydee Varela; Wacho Gonzalez","Unknowns":"","Topics":"Fun; Holiday; Party","WritingMedia":"Computer printed","StampColor":"","PenColors":"","CompPrintColors":"Grey","Type":"Kodak","Corners":"Pointed","Orienation":"N/A","Size":"4.25 x 3.5","HowMany":"Two","Frame":"White Frame","Shape":"Square","Color":"Color","WritingLocation":"Back","Unix":"","Date":"Unknown","Location":"","Neighborhood_Or_SecondCity":"","City":"Guayaquil","State":"","Country":"Ecuador","Description":"","ImageUrl1":"Assets/Thumbnails/056_Front.jpeg","ImageUrl2":"","ImageUrl3":"","ImageUrl4":""},{"Title":"Women working at factory","PeopleinThePhoto":"Elsie Gonzalez; Co-workers","FamilyandFriends":"Elsie Gonzalez; ","Unknowns":"Co-workers","Topics":"Fashion; Food; Work","WritingMedia":"Computer printed","StampColor":"","PenColors":"","CompPrintColors":"Grey","Type":"Kodak","Corners":"Rounded","Orienation":"Landscape","Size":"3.25 x 5","HowMany":"Group","Frame":"No Frame","Shape":"Rectangle","Color":"Color","WritingLocation":"Back","Unix":"170380800","Date":"May 27 1975","Location":"","Neighborhood_Or_SecondCity":"","City":"New York","State":"New York","Country":"United States","Description":"","ImageUrl1":"Assets/Thumbnails/057_Front.jpeg","ImageUrl2":"","ImageUrl3":"","ImageUrl4":""},{"Title":"Sisters at school","PeopleinThePhoto":"Carol Gonzalez; Diana Gonzalez; Evelyn Gonzalez; Sildey Gonzalez","FamilyandFriends":"Carol Gonzalez; Diana Gonzalez; Evelyn Gonzalez; Sildey Gonzalez","Unknowns":"","Topics":"Fashion; School ","WritingMedia":"Pen; Computer printed","StampColor":"","PenColors":"Blue","CompPrintColors":"Grey","Type":"Kodak","Corners":"Rounded","Orienation":"Portrait","Size":"3.5 x 5","HowMany":"Group","Frame":"No Frame","Shape":"Rectangle","Color":"Color","WritingLocation":"Back","Unix":"","Date":"Unknown","Location":"","Neighborhood_Or_SecondCity":"","City":"Guayaquil","State":"","Country":"Ecuador","Description":"","ImageUrl1":"Assets/Thumbnails/058_Front.jpeg","ImageUrl2":"","ImageUrl3":"","ImageUrl4":""},{"Title":"Communion","PeopleinThePhoto":"Mabel Avila; Elsie Gonzalez, Hugo Gonzalez; ","FamilyandFriends":"Mabel Avila; Elsie Gonzalez, Hugo Gonzalez; ","Unknowns":"","Topics":"Communion; Fashion; Traditions","WritingMedia":"","StampColor":"","PenColors":"","CompPrintColors":"","Type":"Unknown","Corners":"Pointed","Orienation":"Portrait","Size":"3.5 x 5.5","HowMany":"Group","Frame":"White Frame","Shape":"Rectangle","Color":"Black & White","WritingLocation":"","Unix":"","Date":"Unknown","Location":"","Neighborhood_Or_SecondCity":"","City":"Guayaquil","State":"","Country":"Ecuador","Description":"","ImageUrl1":"Assets/Thumbnails/059_Front.jpeg","ImageUrl2":"","ImageUrl3":"","ImageUrl4":""},{"Title":"Visiting Graves","PeopleinThePhoto":"Alberto Varela","FamilyandFriends":"Alberto Varela","Unknowns":"","Topics":"Traditions; Vacation","WritingMedia":"Pen; Computer printed","StampColor":"","PenColors":"Blue","CompPrintColors":"Grey","Type":"Konica","Corners":"Pointed","Orienation":"Landscape","Size":"5 x 3.5","HowMany":"One","Frame":"No Frame","Shape":"Rectangle","Color":"Color","WritingLocation":"None","Unix":"902016000","Date":"August 2 1998","Location":"","Neighborhood_Or_SecondCity":"","City":"Cali","State":"","Country":"Colombia","Description":"","ImageUrl1":"Assets/Thumbnails/060_Front.jpeg","ImageUrl2":"","ImageUrl3":"","ImageUrl4":""},{"Title":"Spirit of the Hudson trip","PeopleinThePhoto":"Alberto Varela; Haydee Varela","FamilyandFriends":"Alberto Varela; Haydee Varela","Unknowns":"","Topics":"Fashion; Party","WritingMedia":"Pen; Computer printed","StampColor":"","PenColors":"Black","CompPrintColors":"Grey","Type":"Kodak","Corners":"Pointed","Orienation":"Landscape","Size":"5 x 7","HowMany":"Two ","Frame":"No Frame","Shape":"Rectangle","Color":"Color","WritingLocation":"Back","Unix":"848620800","Date":"November 22 1996","Location":"","Neighborhood_Or_SecondCity":"","City":"New York","State":"New York","Country":"United States","Description":"","ImageUrl1":"Assets/Thumbnails/061_Front.jpeg","ImageUrl2":"","ImageUrl3":"","ImageUrl4":""},{"Title":"Posing ","PeopleinThePhoto":"Hugo Gonzalez","FamilyandFriends":"Hugo Gonzalez","Unknowns":"","Topics":"Fashion; Vacation","WritingMedia":"Pen","StampColor":"","PenColors":"Blue","CompPrintColors":"","Type":"Unknown","Corners":"Pointed","Orienation":"Portrait","Size":"5 x 3.5","HowMany":"One","Frame":"White Frame","Shape":"Rectangle","Color":"Color","WritingLocation":"Back","Unix":"-20131200","Date":"May 13 1969","Location":"","Neighborhood_Or_SecondCity":"","City":"Freeport","State":"","Country":"Bahamas","Description":"","ImageUrl1":"Assets/Thumbnails/062_Front.jpeg","ImageUrl2":"","ImageUrl3":"","ImageUrl4":""},{"Title":"Mother and infant son","PeopleinThePhoto":"Elsie Gonzalez; William Garcia; and Vicente Peñafiel","FamilyandFriends":"Elsie Gonzalez; William Garcia; and Vicente Peñafiel","Unknowns":"","Topics":"Babies; Beach; Vacation","WritingMedia":"Computer printed","StampColor":"","PenColors":"","CompPrintColors":"Grey","Type":"Kodak","Corners":"Rounded","Orienation":"N/A","Size":"3.5 x 3.5","HowMany":"Group","Frame":"No Frame","Shape":"Square","Color":"Color","WritingLocation":"Back","Unix":"","Date":"May 27 1905","Location":"","Neighborhood_Or_SecondCity":"","City":"Salinas","State":"","Country":"Ecuador","Description":"","ImageUrl1":"Assets/Thumbnails/063_Front.png","ImageUrl2":"","ImageUrl3":"","ImageUrl4":""},{"Title":"Little girl posing","PeopleinThePhoto":"Shelmy Cepeda","FamilyandFriends":"Shelmy Cepeda","Unknowns":"","Topics":"Babies; Fashion; Vacation","WritingMedia":"Pen; Computer printed","StampColor":"","PenColors":"Black","CompPrintColors":"Grey","Type":"Kodak","Corners":"Pointed","Orienation":"Portrait","Size":"4 x 5.25","HowMany":"One","Frame":"No Frame","Shape":"Rectangle","Color":"Color","WritingLocation":"Back","Unix":"","Date":"Unknown","Location":"","Neighborhood_Or_SecondCity":"","City":"","State":"","Country":"Ecuador","Description":"","ImageUrl1":"Assets/Thumbnails/064_Front.png","ImageUrl2":"https://drive.google.com/file/d/1vG-8k14-LGGKSMj-KBrQBfO_GJhHZX4t/view?usp=sharing","ImageUrl3":"","ImageUrl4":""},{"Title":"New baby","PeopleinThePhoto":"Mabel Avila; Brigitte Ugarte; ","FamilyandFriends":"Mabel Avila; Brigitte Ugarte; ","Unknowns":"","Topics":"Babies; Holiday","WritingMedia":"Computer printed","StampColor":"","PenColors":"","CompPrintColors":"Grey","Type":"Konica","Corners":"Pointed","Orienation":"Landscape","Size":"5.75 x 4","HowMany":"Two","Frame":"No Frame","Shape":"Rectangle","Color":"Color","WritingLocation":"Back","Unix":"920246400","Date":"March 1 1999","Location":"","Neighborhood_Or_SecondCity":"","City":"Brooklyn","State":"New York","Country":"United States","Description":"","ImageUrl1":"Assets/Thumbnails/065_Front.jpeg","ImageUrl2":"","ImageUrl3":"","ImageUrl4":""},{"Title":"Hugs for the Holiday","PeopleinThePhoto":"Mabel Avila; Brigitte Ugarte","FamilyandFriends":"Mabel Avila; Brigitte Ugarte","Unknowns":"","Topics":"Babies","WritingMedia":"Stamp; Computer printed","StampColor":"Blue","PenColors":"","CompPrintColors":"Grey","Type":"Konica","Corners":"Pointed","Orienation":"Landscape","Size":"4.75 x 3.5","HowMany":"Two ","Frame":"No Frame","Shape":"Rectangle","Color":"Color","WritingLocation":"Back","Unix":"947116800","Date":"January 6 2000","Location":"","Neighborhood_Or_SecondCity":"","City":"Brooklyn","State":"New York","Country":"United States","Description":"","ImageUrl1":"Assets/Thumbnails/066_Front.png","ImageUrl2":"","ImageUrl3":"","ImageUrl4":""},{"Title":"Saluting the flag","PeopleinThePhoto":"Manny Avila;  Unknown children","FamilyandFriends":"Manny Avila;  ","Unknowns":"Unknown children","Topics":"Traditions","WritingMedia":"Pen; Stamp; Computer printed","StampColor":"Black","PenColors":"Black; Blue","CompPrintColors":"Grey","Type":"Kodak","Corners":"Pointed","Orienation":"Landscape","Size":"5 x 3.5","HowMany":"One","Frame":"White Frame","Shape":"Rectangle","Color":"Color","WritingLocation":"Back","Unix":"149904000","Date":"October 2 1974","Location":"","Neighborhood_Or_SecondCity":"","City":"Guayaquil","State":"","Country":"Ecuador","Description":"","ImageUrl1":"Assets/Thumbnails/067_Front.jpeg","ImageUrl2":"","ImageUrl3":"","ImageUrl4":""},{"Title":"Passport Photo","PeopleinThePhoto":"Manny Avila  ","FamilyandFriends":"Manny Avila  ","Unknowns":"","Topics":"Professional Portrait","WritingMedia":"Computer printed","StampColor":"","PenColors":"","CompPrintColors":"Blue","Type":"polaroid","Corners":"Pointed","Orienation":"N/A","Size":"2.5 x 2","HowMany":"One","Frame":"White Frame ","Shape":"Square","Color":"Black & White","WritingLocation":"Back","Unix":"","Date":"Unknown","Location":"","Neighborhood_Or_SecondCity":"","City":"","State":"","Country":"","Description":"","ImageUrl1":"Assets/Thumbnails/068_Front.jpeg","ImageUrl2":"","ImageUrl3":"","ImageUrl4":""},{"Title":"School Dance","PeopleinThePhoto":"Mabel Avila; Unknown man","FamilyandFriends":"Mabel Avila; ","Unknowns":"Unknown man","Topics":"Fashion; School; Traditions","WritingMedia":"Stamp; Computer printed","StampColor":"Red","PenColors":"","CompPrintColors":"Grey","Type":"Kodak","Corners":"Pointed","Orienation":"Portrait","Size":"2.5 x 3.5","HowMany":"One","Frame":"White Frame","Shape":"Rectangle","Color":"Color","WritingLocation":"Back","Unix":"","Date":"Unknown","Location":"","Neighborhood_Or_SecondCity":"","City":"Guayaquil","State":"","Country":"Ecuador","Description":"","ImageUrl1":"Assets/Thumbnails/069_Front.png","ImageUrl2":"https://drive.google.com/file/d/1d8gdEljadkRsXzGUd2GW1xYgCc1vCwg8/view?usp=sharing","ImageUrl3":"","ImageUrl4":""},{"Title":"Day at the Beach","PeopleinThePhoto":"Mabel Avila; Maribel Eugenio; William Garcia; Carol Gonzalez; Diana Gonzalez; Evelyn Gonzalez; Sildey Gonzalez;  Wendy Varela; Unknown man","FamilyandFriends":"Mabel Avila; Maribel Eugenio; William Garcia; Carol Gonzalez; Diana Gonzalez; Evelyn Gonzalez; Sildey Gonzalez;  Wendy Varela; ","Unknowns":"Unknown man","Topics":"Beach; Vacation","WritingMedia":"Computer printed","StampColor":"","PenColors":"","CompPrintColors":"Grey","Type":"Kodak","Corners":"Rounded","Orienation":"Landscape","Size":"5 x 3.5","HowMany":"Group","Frame":"No Frame","Shape":"Rectangle","Color":"Color","WritingLocation":"Back","Unix":"","Date":"Unknown","Location":"","Neighborhood_Or_SecondCity":"","City":"Playas","State":"","Country":"Ecuador","Description":"","ImageUrl1":"Assets/Thumbnails/070_Front.png","ImageUrl2":"","ImageUrl3":"","ImageUrl4":""},{"Title":"First Communion","PeopleinThePhoto":"Alberto Varela","FamilyandFriends":"Alberto Varela","Unknowns":"","Topics":"Communion; Fashion; Professional Portrait; Traditions","WritingMedia":"Pen; Stamp","StampColor":"Black","PenColors":"Black","CompPrintColors":"","Type":"Unknown","Corners":"Pointed","Orienation":"Portrait","Size":"3.75 x 5.5","HowMany":"One","Frame":"White Frame","Shape":"Rectangle","Color":"Black & White","WritingLocation":"Back","Unix":"","Date":"Unknown","Location":"","Neighborhood_Or_SecondCity":"","City":"Cali","State":"","Country":"Colombia","Description":"","ImageUrl1":"Assets/Thumbnails/071_Front.png","ImageUrl2":"https://drive.google.com/file/d/1WZpOK2Wf48cYAuZbnZHMZ3rf1S7jp-qv/view?usp=sharing","ImageUrl3":"","ImageUrl4":""},{"Title":"Day at the River Front","PeopleinThePhoto":"Elsie Gonzalez","FamilyandFriends":"Elsie Gonzalez","Unknowns":"","Topics":"Beach; Vacation","WritingMedia":"Computer printed","StampColor":"","PenColors":"","CompPrintColors":"Grey","Type":"AGFA","Corners":"Pointed","Orienation":"Landscape","Size":"5.25 x 3.5","HowMany":"One","Frame":"No Frame","Shape":"Rectangle","Color":"Black & White","WritingLocation":"Back","Unix":"","Date":"Unknown","Location":"","Neighborhood_Or_SecondCity":"","City":"Guayaquil","State":"","Country":"Ecuador","Description":"","ImageUrl1":"Assets/Thumbnails/072_Front.png","ImageUrl2":"","ImageUrl3":"","ImageUrl4":""},{"Title":"Brother and Sister","PeopleinThePhoto":"Mabel Avila; Manny Avila","FamilyandFriends":"Mabel Avila; Manny Avila","Unknowns":"","Topics":"Babies; Professional Portrait","WritingMedia":"Pen; Stamp","StampColor":"Black","PenColors":"Blue","CompPrintColors":"","Type":"Unknown","Corners":"Pointed","Orienation":"Portrait","Size":"3.25 x 5.5","HowMany":"Two","Frame":"White Frame","Shape":"Rectangle","Color":"Black & White","WritingLocation":"Back","Unix":"-143337600","Date":"June 17 1965","Location":"","Neighborhood_Or_SecondCity":"","City":"Guayaquil","State":"","Country":"Ecuador","Description":"","ImageUrl1":"Assets/Thumbnails/073_Front.png","ImageUrl2":"","ImageUrl3":"","ImageUrl4":""},{"Title":"Sisters and Cousin outing","PeopleinThePhoto":"Wendy Varela; Mabel Avila; William Garcia","FamilyandFriends":"Wendy Varela; Mabel Avila; William Garcia","Unknowns":"","Topics":"Fashion; Vacation","WritingMedia":"Pen; Computer printed","StampColor":"","PenColors":"Blue","CompPrintColors":"Grey","Type":"Kodak","Corners":"Pointed","Orienation":"Portrait","Size":"3.5 x 5.5","HowMany":"Group","Frame":"White Frame","Shape":"Rectangle","Color":"Color","WritingLocation":"Back","Unix":"172627200","Date":"June 22 1975","Location":"","Neighborhood_Or_SecondCity":"","City":"Guayaquil","State":"","Country":"Ecuador","Description":"","ImageUrl1":"Assets/Thumbnails/074_Front.png","ImageUrl2":"https://drive.google.com/file/d/1yiI-R7l-X7Ysf7aB7U-DuEy7ma-_Xiyr/view?usp=sharing","ImageUrl3":"","ImageUrl4":""},{"Title":"Siblings at a wedding","PeopleinThePhoto":"Mabel Avila; Manny Avila","FamilyandFriends":"Mabel Avila; Manny Avila","Unknowns":"","Topics":"Fashion; Professional Portrait; Wedding","WritingMedia":"Pen","StampColor":"","PenColors":"Blue","CompPrintColors":"","Type":"Unknown","Corners":"Pointed","Orienation":"Portrait","Size":"4.5 x 7","HowMany":"Two  ","Frame":"White Frame","Shape":"Rectangle","Color":"Black & White","WritingLocation":"Back","Unix":"-18576000","Date":"May 31 1969","Location":"","Neighborhood_Or_SecondCity":"","City":"Guayaquil","State":"","Country":"Ecuador","Description":"","ImageUrl1":"Assets/Thumbnails/075_Front.png","ImageUrl2":"","ImageUrl3":"","ImageUrl4":""},{"Title":"Cousins posing","PeopleinThePhoto":"William Garcia; Wendy Varela","FamilyandFriends":"William Garcia; Wendy Varela; ","Unknowns":"","Topics":"Fashion","WritingMedia":"Computer printed","StampColor":"","PenColors":"","CompPrintColors":"Grey","Type":"Kodak","Corners":"Rounded","Orienation":"Landscape","Size":"4.25 x 3.5","HowMany":"Two","Frame":"No Frame","Shape":"Rectangle","Color":"Color","WritingLocation":"None","Unix":"","Date":"Unknown","Location":"","Neighborhood_Or_SecondCity":"","City":"Guayaquil","State":"","Country":"Ecuador","Description":"","ImageUrl1":"Assets/Thumbnails/076_Front.png","ImageUrl2":"https://drive.google.com/file/d/1F1bZAXuhF7Nfn7CNU0Z_GmhJcc-QJM3X/view?usp=sharing","ImageUrl3":"","ImageUrl4":""},{"Title":"Family reunion","PeopleinThePhoto":"Salazar Family","FamilyandFriends":"Salazar Family","Unknowns":"","Topics":"Birthday; Party","WritingMedia":"Computer printed","StampColor":"","PenColors":"","CompPrintColors":"Grey","Type":"Kodak","Corners":"Rounded","Orienation":"N/A","Size":"3.5 x 3.25","HowMany":"Group","Frame":"No Frame","Shape":"Square","Color":"Color","WritingLocation":"None","Unix":"","Date":"Unknown","Location":"","Neighborhood_Or_SecondCity":"","City":"Guayaquil","State":"","Country":"Ecuador","Description":"","ImageUrl1":"Assets/Thumbnails/077_Front.png","ImageUrl2":"","ImageUrl3":"","ImageUrl4":""},{"Title":"Coming out of bath","PeopleinThePhoto":"Haydee Varela; Wendy Varela ","FamilyandFriends":"Haydee Varela; Wendy Varela; ","Unknowns":"","Topics":"Babies","WritingMedia":"Pen","StampColor":"","PenColors":"Blue","CompPrintColors":"","Type":"Unknown","Corners":"Pointed","Orienation":"N/A","Size":"3.5  x 3.5","HowMany":"Two","Frame":"White Frame","Shape":"Square","Color":"Color","WritingLocation":"Back","Unix":"114307200","Date":"August 16 1973","Location":"","Neighborhood_Or_SecondCity":"","City":"Brooklyn","State":"New York","Country":"United States","Description":"","ImageUrl1":"Assets/Thumbnails/078_Front.png","ImageUrl2":"https://drive.google.com/file/d/1YxnFD7oanIDl-XhthUWCyh6i5M2T39Cc/view?usp=sharing","ImageUrl3":"","ImageUrl4":""},{"Title":"Walking the caverns","PeopleinThePhoto":"Mariana Gonzalez, Haydee Varela","FamilyandFriends":"Mariana Gonzalez, Haydee Varela; ","Unknowns":"","Topics":"Vacation","WritingMedia":"Computer printed","StampColor":"","PenColors":"","CompPrintColors":"Grey","Type":"Konica","Corners":"Pointed","Orienation":"Landscape","Size":"5.75 x 4","HowMany":"Two","Frame":"Black frame","Shape":"Rectangle","Color":"Color","WritingLocation":"None","Unix":"872812800","Date":"August 29 1997","Location":"Luray Caverns","Neighborhood_Or_SecondCity":"","City":"Luray","State":"Virginia","Country":"United States","Description":"","ImageUrl1":"Assets/Thumbnails/079_Front.png","ImageUrl2":"","ImageUrl3":"","ImageUrl4":""},{"Title":"Dinosaur Ride","PeopleinThePhoto":"Haydee Varela","FamilyandFriends":"Haydee Varela","Unknowns":"","Topics":"Fun; Vacation","WritingMedia":"Stamp; Computer printed","StampColor":"Red","PenColors":"","CompPrintColors":"Grey","Type":"Kodak","Corners":"Pointed","Orienation":"N/A","Size":"3.5 x 3.5","HowMany":"One","Frame":"White Frame","Shape":"Square","Color":"Color","WritingLocation":"Back","Unix":"","Date":"May 22 1905","Location":"Coney Island","Neighborhood_Or_SecondCity":"","City":"Brooklyn","State":"","Country":"United States","Description":"","ImageUrl1":"Assets/Thumbnails/080_Front.png","ImageUrl2":"https://drive.google.com/file/d/1PEG_opgoGYP7L3TYq59OUUBk9UL6x1Ug/view?usp=sharing","ImageUrl3":"","ImageUrl4":""},{"Title":"Yellow Sunglasses","PeopleinThePhoto":"Brigitte Ugarte","FamilyandFriends":"Brigitte Ugarte","Unknowns":"","Topics":"Babies; Fashion","WritingMedia":"Computer printed","StampColor":"","PenColors":"","CompPrintColors":"Grey","Type":"Konica","Corners":"Pointed","Orienation":"Landscape","Size":"4.75 x 3.5","HowMany":"One","Frame":"No Frame","Shape":"Rectangle","Color":"Color","WritingLocation":"Back","Unix":"920246400","Date":"March 1 1999","Location":"","Neighborhood_Or_SecondCity":"","City":"Brooklyn","State":"New York","Country":"United States","Description":"","ImageUrl1":"Assets/Thumbnails/081_Front.png","ImageUrl2":"https://drive.google.com/file/d/13dQylKW4F2pdgn5Iaw-st_tz3K5O1dAC/view?usp=sharing","ImageUrl3":"","ImageUrl4":""},{"Title":"Posing by the pool","PeopleinThePhoto":"Diana Gonzalez ","FamilyandFriends":"Diana Gonzalez ","Unknowns":"","Topics":"Fashion; Vacation","WritingMedia":"Pen; Computer printed","StampColor":"","PenColors":"Black","CompPrintColors":"Grey","Type":"Kodak","Corners":"Pointed","Orienation":"Portrait","Size":"4 x 5","HowMany":"One","Frame":"No Frame","Shape":"Rectangle","Color":"Color","WritingLocation":"Back","Unix":"","Date":"June 17 1905","Location":"","Neighborhood_Or_SecondCity":"","City":"","State":"","Country":"Ecuador","Description":"","ImageUrl1":"Assets/Thumbnails/082_Front.png","ImageUrl2":"https://drive.google.com/file/d/1Cp1ZVQ2Zmc0xmEafJGgQ2kOt1PZm-vPA/view?usp=sharing","ImageUrl3":"","ImageUrl4":""},{"Title":"Eating snacks","PeopleinThePhoto":"Alberto Varela","FamilyandFriends":"Alberto Varela","Unknowns":"","Topics":"Food; Vacation","WritingMedia":"Pen; Computer printed","StampColor":"","PenColors":"Blue","CompPrintColors":"Grey","Type":"Kodak","Corners":"Pointed","Orienation":"Landscape","Size":"4.75 x 3.5","HowMany":"One","Frame":"No Frame","Shape":"Rectangle","Color":"Color","WritingLocation":"Back","Unix":"715737600","Date":"September 6 1992","Location":"","Neighborhood_Or_SecondCity":"","City":"Orlando","State":"Florida","Country":"United States","Description":"","ImageUrl1":"Assets/Thumbnails/083_Front.jpeg","ImageUrl2":"","ImageUrl3":"","ImageUrl4":""},{"Title":"Family posing at Colombia","PeopleinThePhoto":"Alberto Varela; Haydee Varela; Unknown friend","FamilyandFriends":"Alberto Varela; Haydee Varela; ","Unknowns":"Unknown friend","Topics":"Vacation","WritingMedia":"Pen; Computer printed","StampColor":"","PenColors":"Black","CompPrintColors":"Grey","Type":"Kodak","Corners":"Pointed","Orienation":"Landscape","Size":"5.75 x 4","HowMany":"Group","Frame":"No Frame","Shape":"Rectangle","Color":"Color","WritingLocation":"Back","Unix":"1188604800","Date":"September 1 2007","Location":"","Neighborhood_Or_SecondCity":"","City":"Cali","State":"","Country":"Colombia","Description":"","ImageUrl1":"Assets/Thumbnails/084_Front.png","ImageUrl2":"https://drive.google.com/file/d/1rO_6YmiZx0Vm9n9OG0MNCzFFBcCzWeCr/view?usp=sharing","ImageUrl3":"","ImageUrl4":""},{"Title":"Posing inside the Lucerne Caverns","PeopleinThePhoto":"Wendy Varela","FamilyandFriends":"Wendy Varela","Unknowns":"","Topics":"Vacation","WritingMedia":"Computer printed","StampColor":"","PenColors":"","CompPrintColors":"Grey","Type":"Kodak","Corners":"Pointed","Orienation":"Portrait","Size":"4 x 6","HowMany":"One","Frame":"Black Frame","Shape":"Rectangle","Color":"Color","WritingLocation":"Back","Unix":"872812800","Date":"August 29 1997","Location":"Luray Caverns","Neighborhood_Or_SecondCity":"","City":"Luray","State":"Virginia","Country":"United States","Description":"","ImageUrl1":"Assets/Thumbnails/085_Front.png","ImageUrl2":"https://drive.google.com/file/d/11DwMt2ylcFJ-nBEmGf_jvykh73Bz5Not/view?usp=sharing","ImageUrl3":"","ImageUrl4":""},{"Title":"First Communion ","PeopleinThePhoto":"Haydee Varela;  Unknown child; Nun","FamilyandFriends":"Haydee Varela;  ","Unknowns":"Unknown child; Nun","Topics":"Communion; Fashion; Traditions","WritingMedia":"Pencil; Computer printed","StampColor":"","PenColors":"","CompPrintColors":"Grey","Type":"Unknown","Corners":"Scalloped","Orienation":"Portrait","Size":"3.5 x 5.25","HowMany":"Group","Frame":"White Frame","Shape":"Rectangle","Color":"Black & White","WritingLocation":"Back","Unix":"","Date":"May 13 1905","Location":"","Neighborhood_Or_SecondCity":"","City":"Ecuador","State":"","Country":"Ecuador","Description":"","ImageUrl1":"Assets/Thumbnails/086_Front.png","ImageUrl2":"","ImageUrl3":"","ImageUrl4":""},{"Title":"Posing at the Beach","PeopleinThePhoto":"Haydee Varela;  Unknown men","FamilyandFriends":"Haydee Varela;  ","Unknowns":"Unknown men","Topics":"Beach; Fashion; Vacation","WritingMedia":"Computer printed","StampColor":"","PenColors":"","CompPrintColors":"Grey","Type":"AGFA","Corners":"Zig-Zag ","Orienation":"Portrait","Size":"4.5 x 7","HowMany":"One","Frame":"White Frame","Shape":"Rectangle","Color":"Black & White","WritingLocation":"None","Unix":"","Date":"May 19 1905","Location":"","Neighborhood_Or_SecondCity":"","City":"Libertad","State":"","Country":"Ecuador","Description":"","ImageUrl1":"Assets/Thumbnails/087_Front.png","ImageUrl2":"","ImageUrl3":"","ImageUrl4":""},{"Title":"Babies on the sofas","PeopleinThePhoto":"Wendy Varela;  Unknown child","FamilyandFriends":"Wendy Varela;  ","Unknowns":"Unknown child ","Topics":"Babies","WritingMedia":"Computer printed","StampColor":"","PenColors":"","CompPrintColors":"Black; Grey","Type":"Kodak","Corners":"Pointed","Orienation":"Portrait","Size":"2.5 x 3.5","HowMany":"Two","Frame":"White Frame","Shape":"Rectangle","Color":"Color","WritingLocation":"Front and back","Unix":"","Date":"May 26 1905","Location":"","Neighborhood_Or_SecondCity":"","City":"Brooklyn","State":"New York","Country":"United States","Description":"","ImageUrl1":"Assets/Thumbnails/088_Front.png","ImageUrl2":"","ImageUrl3":"","ImageUrl4":""},{"Title":"Cousins at the Park","PeopleinThePhoto":"William Garcia; Carol Gonzalez; Diana Gonzalez; Wendy Varela","FamilyandFriends":"William Garcia; Carol Gonzalez; Diana Gonzalez; Wendy Varela","Unknowns":"","Topics":"Fun;Vacation","WritingMedia":"Computer printed","StampColor":"","PenColors":"","CompPrintColors":"Grey","Type":"Kodak","Corners":"Rounded","Orienation":"Landscape","Size":"5 x 3.5","HowMany":"Group","Frame":"No Frame","Shape":"Rectangle","Color":"Color","WritingLocation":"Back","Unix":"","Date":"June 4 1905","Location":"","Neighborhood_Or_SecondCity":"","City":"Guayaquil","State":"","Country":"Ecuador","Description":"","ImageUrl1":"Assets/Thumbnails/089_Front.png","ImageUrl2":"","ImageUrl3":"","ImageUrl4":""},{"Title":"Couple Posing","PeopleinThePhoto":"Alberto Varela; Haydee Varela","FamilyandFriends":"Alberto Varela; Haydee Varela; ","Unknowns":"","Topics":"Fashion; Vacation","WritingMedia":"Computer printed","StampColor":"","PenColors":"","CompPrintColors":"Grey","Type":"Kodak","Corners":"Rounded","Orienation":"Portrait","Size":"3.5 x 4.25","HowMany":"Two","Frame":"No Frame","Shape":"Rectangle","Color":"Color","WritingLocation":"Back","Unix":"","Date":"May 23 1905","Location":"","Neighborhood_Or_SecondCity":"","City":"","State":"","Country":"United States","Description":"","ImageUrl1":"Assets/Thumbnails/090_Front.png","ImageUrl2":"","ImageUrl3":"","ImageUrl4":""},{"Title":"Navy graduate with family","PeopleinThePhoto":"Mabel Avila; Manny Avila;  William Garcia; Mariana Gonzalez; Wendy Varela","FamilyandFriends":"Mabel Avila; Manny Avila;  William Garcia; Mariana Gonzalez; Wendy Varela; ","Unknowns":"","Topics":"Fashion; Graduation","WritingMedia":"","StampColor":"","PenColors":"","CompPrintColors":"","Type":"Unknown","Corners":"Rounded","Orienation":"Landscape","Size":"4.25 x 3.5","HowMany":"Group","Frame":"No Frame","Shape":"Rectangle","Color":"Color","WritingLocation":"","Unix":"397008000","Date":"August 1 1982","Location":"","Neighborhood_Or_SecondCity":"","City":"Orlando","State":"Florida","Country":"United States","Description":"","ImageUrl1":"Assets/Thumbnails/091_Front.png","ImageUrl2":"","ImageUrl3":"","ImageUrl4":""},{"Title":"First Communion","PeopleinThePhoto":"Doris Gonzalez; Mariana Gonzalez; Alberto Varela; Haydee Varela","FamilyandFriends":"Doris Gonzalez; Mariana Gonzalez; Alberto Varela; Haydee Varela; ","Unknowns":"","Topics":"Communion; Fashion; Traditions","WritingMedia":"Pen; Computer printed","StampColor":"","PenColors":"Black","CompPrintColors":"Grey","Type":"Kodak","Corners":"Pointed","Orienation":"Portrait","Size":"4 x 6","HowMany":"Group","Frame":"No Frame","Shape":"Rectangle","Color":"Color","WritingLocation":"Back","Unix":"734227200","Date":"April 8 1993","Location":"","Neighborhood_Or_SecondCity":"","City":"Astoria","State":"New York","Country":"United States","Description":"","ImageUrl1":"Assets/Thumbnails/092_Front.png","ImageUrl2":"","ImageUrl3":"","ImageUrl4":""},{"Title":"Snow Day","PeopleinThePhoto":"Alberto Varela; Wendy Varela  ","FamilyandFriends":"Alberto Varela; Wendy Varela;  ","Unknowns":"","Topics":"Babies; Snow Day","WritingMedia":"Stamp; Computer printed","StampColor":"Red","PenColors":"","CompPrintColors":"Grey","Type":"Kodak","Corners":"Pointed","Orienation":"N/A","Size":"3.5 x 3.5","HowMany":"Two","Frame":"White Frame","Shape":"Square","Color":"Color","WritingLocation":"Back","Unix":"128908800","Date":"February 1 1974","Location":"","Neighborhood_Or_SecondCity":"","City":"Brooklyn","State":"New York","Country":"United States","Description":"","ImageUrl1":"Assets/Thumbnails/093_Front.png","ImageUrl2":"","ImageUrl3":"","ImageUrl4":""},{"Title":"Cousins Holding Hands","PeopleinThePhoto":"William Garcia; Carol Gonzalez; Diana Gonzalez; Wendy Varela","FamilyandFriends":"William Garcia; Carol Gonzalez; Diana Gonzalez; Wendy Varela; ","Unknowns":"","Topics":"Fun","WritingMedia":"Computer printed","StampColor":"","PenColors":"","CompPrintColors":"Grey","Type":"Kodak","Corners":"Rounded","Orienation":"Landscape","Size":"4.5 x 3.5","HowMany":"Two","Frame":"No Frame","Shape":"Rectangle","Color":"Color","WritingLocation":"Back","Unix":"","Date":"June 2 1905","Location":"","Neighborhood_Or_SecondCity":"","City":"Brooklyn","State":"New York","Country":"United States","Description":"","ImageUrl1":"Assets/Thumbnails/094_Front.png","ImageUrl2":"","ImageUrl3":"","ImageUrl4":""},{"Title":"Siblings","PeopleinThePhoto":"Mabel Avila; Manny Avila; Wendy Varela  ","FamilyandFriends":"Mabel Avila; Manny Avila; Wendy Varela;  ","Unknowns":"","Topics":"Fun; Holiday","WritingMedia":"Computer printed","StampColor":"","PenColors":"","CompPrintColors":"Grey","Type":"Kodak","Corners":"Pointed","Orienation":"Landscape","Size":"4.75 x 5.5","HowMany":"Group","Frame":"No Frame","Shape":"Rectangle","Color":"Color","WritingLocation":"Back","Unix":"472780800","Date":"December 25 1984","Location":"","Neighborhood_Or_SecondCity":"","City":"Brooklyn","State":"New York","Country":"United States","Description":"","ImageUrl1":"Assets/Thumbnails/095_Front.png","ImageUrl2":"","ImageUrl3":"","ImageUrl4":""},{"Title":"Purse Posing","PeopleinThePhoto":"Mabel Avila","FamilyandFriends":"Mabel Avila","Unknowns":"","Topics":"Fashion; Un Paseo","WritingMedia":"Computer printed","StampColor":"","PenColors":"","CompPrintColors":"Grey","Type":"AGFA","Corners":"Pointed","Orienation":"Portrait","Size":"3.5 x 5.5","HowMany":"One","Frame":"White Frame","Shape":"Rectangle","Color":"Black & White","WritingLocation":"Back","Unix":"","Date":"May 20 1905","Location":"","Neighborhood_Or_SecondCity":"","City":"Guayaquil","State":"","Country":"Ecuador","Description":"","ImageUrl1":"Assets/Thumbnails/096_Front.png","ImageUrl2":"https://drive.google.com/file/d/19abPZ5sOHN2F_QholiFYozORq3o6kGQt/view?usp=sharing","ImageUrl3":"","ImageUrl4":""},{"Title":"First Communion Cake Posing","PeopleinThePhoto":"Doris Gonzalez","FamilyandFriends":"Doris Gonzalez","Unknowns":"","Topics":"Communion; Fashion; Traditions","WritingMedia":"Pen; Computer printed","StampColor":"","PenColors":"Black","CompPrintColors":"Grey","Type":"Kodak","Corners":"Pointed","Orienation":"Landscape","Size":"6 x 4","HowMany":"One","Frame":"None","Shape":"Rectangle","Color":"Color","WritingLocation":"Back","Unix":"734227200","Date":"April 8 1993","Location":"","Neighborhood_Or_SecondCity":"","City":"Astoria","State":"New York","Country":"United States","Description":"","ImageUrl1":"Assets/Thumbnails/097_Front.png","ImageUrl2":"https://drive.google.com/file/d/1MB2OWSiYZ0gET_jYjZ2_gYTo7vfo5ANb/view?usp=sharing","ImageUrl3":"","ImageUrl4":""},{"Title":"Wendy's brithday","PeopleinThePhoto":"Mariana Gonzalez; Haydee Varela; Wendy Varela","FamilyandFriends":"Mariana Gonzalez; Haydee Varela; Wendy Varela","Unknowns":"","Topics":"Birthday; Fashion","WritingMedia":"Computer printed","StampColor":"","PenColors":"","CompPrintColors":"Grey","Type":"AGFA","Corners":"Pointed","Orienation":"Landscape","Size":"6 x 4","HowMany":"Group","Frame":"None","Shape":"Rectangle","Color":"Color","WritingLocation":"Back","Unix":"103507200","Date":"April 13 1973","Location":"","Neighborhood_Or_SecondCity":"","City":"Brooklyn","State":"New York","Country":"United States","Description":"","ImageUrl1":"Assets/Thumbnails/098_Front.png","ImageUrl2":"https://drive.google.com/file/d/1rDV3NnxQac9C1ypRtxUddFCjuPMGdFNU/view?usp=sharing","ImageUrl3":"","ImageUrl4":""},{"Title":"High School Graduation","PeopleinThePhoto":"Mabel Avila; Manny Avila; Mariana Gonzalez; Haydee Varela","FamilyandFriends":"Mabel Avila; Manny Avila; Mariana Gonzalez; Haydee Varela","Unknowns":"","Topics":"Fashion; Graduation; School","WritingMedia":"Computer printed","StampColor":"","PenColors":"","CompPrintColors":"Grey","Type":"Kodak","Corners":"Pointed","Orienation":"Landcape","Size":"5.25 x 4","HowMany":"Group","Frame":"None","Shape":"Rectangle","Color":"Color","WritingLocation":"Back","Unix":"391737600","Date":"June 1 1982","Location":"","Neighborhood_Or_SecondCity":"","City":"Brooklyn","State":"New York","Country":"United States","Description":"","ImageUrl1":"Assets/Thumbnails/099_Front.png","ImageUrl2":"https://drive.google.com/file/d/1_MCyek0mPTAZ0rYqHYQHdKvN-CfY04aj/view?usp=sharing","ImageUrl3":"","ImageUrl4":""},{"Title":"Sunday Strolling","PeopleinThePhoto":"Esmeralda Gonzalez; Alfredo Medina; Alfredo Jr. Medina; Grey Yvonne Medina; Jenny Medina","FamilyandFriends":"Esmeralda Gonzalez; Alfredo Medina; Alfredo Jr. Medina; Grey Yvonne Medina; Jenny Medina","Unknowns":"","Topics":"Fashion; Un Paseo","WritingMedia":"Pen; Computer printed","StampColor":"","PenColors":"Blue","CompPrintColors":"Grey","Type":"AGFA","Corners":"Scalloped","Orienation":"Landscape","Size":"5.25 x 3.5","HowMany":"Group","Frame":"White Frame","Shape":"Rectangle","Color":"Black & White","WritingLocation":"Back","Unix":"","Date":"May 13 1905","Location":"","Neighborhood_Or_SecondCity":"","City":"Guayaquil","State":"","Country":"Ecuador","Description":"","ImageUrl1":"Assets/Thumbnails/100_Front.png","ImageUrl2":"https://drive.google.com/file/d/1GrqHz2vuFk9RDrIGk3dwOO66sFjwEwUT/view?usp=sharing","ImageUrl3":"","ImageUrl4":""}]